AUTHORS.rst
HISTORY.rst
LICENSE
MANIFEST.in
README.md
setup.cfg
setup.py
datapool/__init__.py
datapool/bunch.py
datapool/comment_model.py
datapool/config.py
datapool/data_conversion.py
datapool/database.py
datapool/dispatcher.py
datapool/errors.py
datapool/http_server.py
datapool/interpreter_bridge.py
datapool/julia_runner.py
datapool/landing_zone.py
datapool/logger.py
datapool/main.py
datapool/matlab_runner.py
datapool/observer.py
datapool/python_runner.py
datapool/r_runner.py
datapool/utils.py
datapool/yaml_stuff.py
datapool.egg-info/PKG-INFO
datapool.egg-info/SOURCES.txt
datapool.egg-info/dependency_links.txt
datapool.egg-info/entry_points.txt
datapool.egg-info/not-zip-safe
datapool.egg-info/requires.txt
datapool.egg-info/top_level.txt
datapool/commands/__init__.py
datapool/commands/add.py
datapool/commands/check.py
datapool/commands/check_config.py
datapool/commands/create_example.py
datapool/commands/delete.py
datapool/commands/init_config.py
datapool/commands/init_db.py
datapool/commands/run_simple_server.py
datapool/commands/start_develop.py
datapool/commands/update_operational.py
datapool/instance/__init__.py
datapool/instance/config_handling.py
datapool/instance/converters.py
datapool/instance/db_objects.py
datapool/instance/domain_objects.py
datapool/instance/domain_objects_checker.py
datapool/instance/landing_zone_structure.py
datapool/instance/main.py
datapool/instance/parameters_model.py
datapool/instance/pretty_printers.py
datapool/instance/signal_model.py
datapool/instance/site_and_picture_model.py
datapool/instance/source_model.py
datapool/instance/source_type_model.py
datapool/instance/uniform_file_format.py
datapool/instance/yaml_parsers.py
datapool/templates/__init__.py
datapool/templates/base.py
datapool/templates/parameter.py
datapool/templates/site.py
datapool/templates/source.py
datapool/templates/source_type.py
datapool/templates/utils.py