Metadata-Version: 1.2
Name: datapool
Version: 0.6.8
Summary: EAWAG data warehouse
Home-page: https://github.com/uweschmitt/datapool
Author: Uwe Schmitt
Author-email: uwe.schmitt@id.ethz.ch
License: ISCL
Keywords: datapool
Platform: UNKNOWN
Classifier: Development Status :: 2 - Pre-Alpha
Classifier: Intended Audience :: Developers
Classifier: License :: OSI Approved :: ISC License (ISCL)
Classifier: Natural Language :: English
Classifier: Programming Language :: Python :: 3.4
Classifier: Programming Language :: Python :: 3.5
Requires-Python: >3.5
